<?xml version="1.0" encoding="UTF-8"?>
<OfficeApp xmlns="http://schemas.microsoft.com/office/appforoffice/1.1"
           xmlns:xsi="http://www.w3.org/2001/XMLSchema-instance"
           xsi:type="TaskPaneApp">

  <Id>a1b2c3d4-e5f6-7890-abcd-ef1234567890</Id>
  <Version>1.0.0.0</Version>
  <ProviderName>BI Publisher Tools</ProviderName>
  <DefaultLocale>en-US</DefaultLocale>
  <DisplayName DefaultValue="BI Publisher"/>
  <Description DefaultValue="Oracle BI Publisher Template Builder for macOS — design report templates in Word."/>
  <IconUrl DefaultValue="https://localhost:3000/images/ico-field-32.png"/>
  <HighResolutionIconUrl DefaultValue="https://localhost:3000/images/ico-field-80.png"/>
  <SupportUrl DefaultValue="https://localhost:3000/taskpane.html?panel=help"/>

  <Hosts><Host Name="Document"/></Hosts>
  <DefaultSettings><SourceLocation DefaultValue="https://localhost:3000/taskpane.html"/></DefaultSettings>
  <Permissions>ReadWriteDocument</Permissions>

  <VersionOverrides xmlns="http://schemas.microsoft.com/office/taskpaneappversionoverrides"
                    xmlns:bt="http://schemas.microsoft.com/office/officeappbasictypes/1.0"
                    xsi:type="VersionOverridesV1_0">
    <Hosts>
      <Host xsi:type="Document">
        <DesktopFormFactor>

          <GetStarted>
            <Title resid="getStarted.Title"/>
            <Description resid="getStarted.Desc"/>
            <LearnMoreUrl resid="url.taskpane"/>
          </GetStarted>

          <FunctionFile resid="url.commands"/>

          <ExtensionPoint xsi:type="PrimaryCommandSurface">
            <CustomTab id="TabPublisher">

              <!-- ============ LOAD DATA (2 controls) ============ -->
              <Group id="grpLoadData">
                <Label resid="grp.data"/>
                <Icon><bt:Image size="16" resid="ico.samplexml.16"/><bt:Image size="32" resid="ico.samplexml.32"/><bt:Image size="80" resid="ico.samplexml.80"/></Icon>

                <Control xsi:type="Button" id="btnSampleXML">
                  <Label resid="lbl.samplexml"/>
                  <Supertip><Title resid="lbl.samplexml"/><Description resid="tip.samplexml"/></Supertip>
                  <Icon><bt:Image size="16" resid="ico.samplexml.16"/><bt:Image size="32" resid="ico.samplexml.32"/><bt:Image size="80" resid="ico.samplexml.80"/></Icon>
                  <Action xsi:type="ShowTaskpane">
                    <TaskpaneId>BIP</TaskpaneId>
                    <SourceLocation resid="url.samplexml"/>
                  </Action>
                </Control>

                <Control xsi:type="Button" id="btnXMLSchema">
                  <Label resid="lbl.xmlschema"/>
                  <Supertip><Title resid="lbl.xmlschema"/><Description resid="tip.xmlschema"/></Supertip>
                  <Icon><bt:Image size="16" resid="ico.xmlschema.16"/><bt:Image size="32" resid="ico.xmlschema.32"/><bt:Image size="80" resid="ico.xmlschema.80"/></Icon>
                  <Action xsi:type="ShowTaskpane">
                    <TaskpaneId>BIP</TaskpaneId>
                    <SourceLocation resid="url.xmlschema"/>
                  </Action>
                </Control>
              </Group>

              <!-- ============ INSERT (5 buttons + 1 menu = 6) ============ -->
              <Group id="grpInsert">
                <Label resid="grp.insert"/>
                <Icon><bt:Image size="16" resid="ico.field.16"/><bt:Image size="32" resid="ico.field.32"/><bt:Image size="80" resid="ico.field.80"/></Icon>

                <Control xsi:type="Button" id="btnField">
                  <Label resid="lbl.field"/>
                  <Supertip><Title resid="lbl.field"/><Description resid="tip.field"/></Supertip>
                  <Icon><bt:Image size="16" resid="ico.field.16"/><bt:Image size="32" resid="ico.field.32"/><bt:Image size="80" resid="ico.field.80"/></Icon>
                  <Action xsi:type="ShowTaskpane">
                    <TaskpaneId>BIP</TaskpaneId>
                    <SourceLocation resid="url.field"/>
                  </Action>
                </Control>

                <Control xsi:type="Button" id="btnTableWizard">
                  <Label resid="lbl.tablewiz"/>
                  <Supertip><Title resid="lbl.tablewiz"/><Description resid="tip.tablewiz"/></Supertip>
                  <Icon><bt:Image size="16" resid="ico.tablewiz.16"/><bt:Image size="32" resid="ico.tablewiz.32"/><bt:Image size="80" resid="ico.tablewiz.80"/></Icon>
                  <Action xsi:type="ShowTaskpane">
                    <TaskpaneId>BIP</TaskpaneId>
                    <SourceLocation resid="url.tablewiz"/>
                  </Action>
                </Control>

                <Control xsi:type="Button" id="btnChart">
                  <Label resid="lbl.chart"/>
                  <Supertip><Title resid="lbl.chart"/><Description resid="tip.chart"/></Supertip>
                  <Icon><bt:Image size="16" resid="ico.chart.16"/><bt:Image size="32" resid="ico.chart.32"/><bt:Image size="80" resid="ico.chart.80"/></Icon>
                  <Action xsi:type="ShowTaskpane">
                    <TaskpaneId>BIP</TaskpaneId>
                    <SourceLocation resid="url.chart"/>
                  </Action>
                </Control>

                <Control xsi:type="Button" id="btnPivotTable">
                  <Label resid="lbl.pivot"/>
                  <Supertip><Title resid="lbl.pivot"/><Description resid="tip.pivot"/></Supertip>
                  <Icon><bt:Image size="16" resid="ico.pivot.16"/><bt:Image size="32" resid="ico.pivot.32"/><bt:Image size="80" resid="ico.pivot.80"/></Icon>
                  <Action xsi:type="ShowTaskpane">
                    <TaskpaneId>BIP</TaskpaneId>
                    <SourceLocation resid="url.pivot"/>
                  </Action>
                </Control>

                <Control xsi:type="Menu" id="menuMoreInsert">
                  <Label resid="lbl.more"/>
                  <Supertip><Title resid="lbl.more"/><Description resid="tip.more"/></Supertip>
                  <Icon><bt:Image size="16" resid="ico.allfields.16"/><bt:Image size="32" resid="ico.allfields.32"/><bt:Image size="80" resid="ico.allfields.80"/></Icon>
                  <Items>
                    <Item id="itemTableForm">
                      <Label resid="lbl.tableform"/>
                      <Supertip><Title resid="lbl.tableform"/><Description resid="tip.tableform"/></Supertip>
                      <Icon><bt:Image size="16" resid="ico.tableform.16"/><bt:Image size="32" resid="ico.tableform.32"/><bt:Image size="80" resid="ico.tableform.80"/></Icon>
                      <Action xsi:type="ExecuteFunction"><FunctionName>cmdTableForm</FunctionName></Action>
                    </Item>
                    <Item id="itemRepGroup">
                      <Label resid="lbl.repgroup"/>
                      <Supertip><Title resid="lbl.repgroup"/><Description resid="tip.repgroup"/></Supertip>
                      <Icon><bt:Image size="16" resid="ico.repgroup.16"/><bt:Image size="32" resid="ico.repgroup.32"/><bt:Image size="80" resid="ico.repgroup.80"/></Icon>
                      <Action xsi:type="ExecuteFunction"><FunctionName>cmdRepeatingGroup</FunctionName></Action>
                    </Item>
                    <Item id="itemCondFmt">
                      <Label resid="lbl.condfmt"/>
                      <Supertip><Title resid="lbl.condfmt"/><Description resid="tip.condfmt"/></Supertip>
                      <Icon><bt:Image size="16" resid="ico.condfmt.16"/><bt:Image size="32" resid="ico.condfmt.32"/><bt:Image size="80" resid="ico.condfmt.80"/></Icon>
                      <Action xsi:type="ExecuteFunction"><FunctionName>cmdCondFormat</FunctionName></Action>
                    </Item>
                    <Item id="itemCondReg">
                      <Label resid="lbl.condreg"/>
                      <Supertip><Title resid="lbl.condreg"/><Description resid="tip.condreg"/></Supertip>
                      <Icon><bt:Image size="16" resid="ico.condreg.16"/><bt:Image size="32" resid="ico.condreg.32"/><bt:Image size="80" resid="ico.condreg.80"/></Icon>
                      <Action xsi:type="ExecuteFunction"><FunctionName>cmdCondRegion</FunctionName></Action>
                    </Item>
                    <Item id="itemAllFields">
                      <Label resid="lbl.allfields"/>
                      <Supertip><Title resid="lbl.allfields"/><Description resid="tip.allfields"/></Supertip>
                      <Icon><bt:Image size="16" resid="ico.allfields.16"/><bt:Image size="32" resid="ico.allfields.32"/><bt:Image size="80" resid="ico.allfields.80"/></Icon>
                      <Action xsi:type="ExecuteFunction"><FunctionName>cmdAllFields</FunctionName></Action>
                    </Item>
                  </Items>
                </Control>
              </Group>

              <!-- ============ PREVIEW (1 button) ============ -->
              <Group id="grpPreview">
                <Label resid="grp.preview"/>
                <Icon><bt:Image size="16" resid="ico.preview.16"/><bt:Image size="32" resid="ico.preview.32"/><bt:Image size="80" resid="ico.preview.80"/></Icon>

                <Control xsi:type="Button" id="btnPreview">
                  <Label resid="lbl.preview"/>
                  <Supertip><Title resid="lbl.preview"/><Description resid="tip.preview"/></Supertip>
                  <Icon><bt:Image size="16" resid="ico.preview.16"/><bt:Image size="32" resid="ico.preview.32"/><bt:Image size="80" resid="ico.preview.80"/></Icon>
                  <Action xsi:type="ShowTaskpane">
                    <TaskpaneId>BIP</TaskpaneId>
                    <SourceLocation resid="url.preview"/>
                  </Action>
                </Control>
              </Group>

              <!-- ============ TOOLS (5 buttons) ============ -->
              <Group id="grpTools">
                <Label resid="grp.tools"/>
                <Icon><bt:Image size="16" resid="ico.fieldbrowser.16"/><bt:Image size="32" resid="ico.fieldbrowser.32"/><bt:Image size="80" resid="ico.fieldbrowser.80"/></Icon>

                <Control xsi:type="Button" id="btnFieldBrowser">
                  <Label resid="lbl.fieldbrowser"/>
                  <Supertip><Title resid="lbl.fieldbrowser"/><Description resid="tip.fieldbrowser"/></Supertip>
                  <Icon><bt:Image size="16" resid="ico.fieldbrowser.16"/><bt:Image size="32" resid="ico.fieldbrowser.32"/><bt:Image size="80" resid="ico.fieldbrowser.80"/></Icon>
                  <Action xsi:type="ShowTaskpane">
                    <TaskpaneId>BIP</TaskpaneId>
                    <SourceLocation resid="url.fieldbrowser"/>
                  </Action>
                </Control>

                <Control xsi:type="Button" id="btnValidate">
                  <Label resid="lbl.validate"/>
                  <Supertip><Title resid="lbl.validate"/><Description resid="tip.validate"/></Supertip>
                  <Icon><bt:Image size="16" resid="ico.validate.16"/><bt:Image size="32" resid="ico.validate.32"/><bt:Image size="80" resid="ico.validate.80"/></Icon>
                  <Action xsi:type="ShowTaskpane">
                    <TaskpaneId>BIP</TaskpaneId>
                    <SourceLocation resid="url.validate"/>
                  </Action>
                </Control>

                <Control xsi:type="Button" id="btnAccessibility">
                  <Label resid="lbl.a11y"/>
                  <Supertip><Title resid="lbl.a11y"/><Description resid="tip.a11y"/></Supertip>
                  <Icon><bt:Image size="16" resid="ico.a11y.16"/><bt:Image size="32" resid="ico.a11y.32"/><bt:Image size="80" resid="ico.a11y.80"/></Icon>
                  <Action xsi:type="ShowTaskpane">
                    <TaskpaneId>BIP</TaskpaneId>
                    <SourceLocation resid="url.a11y"/>
                  </Action>
                </Control>

                <Control xsi:type="Button" id="btnTranslation">
                  <Label resid="lbl.translation"/>
                  <Supertip><Title resid="lbl.translation"/><Description resid="tip.translation"/></Supertip>
                  <Icon><bt:Image size="16" resid="ico.translation.16"/><bt:Image size="32" resid="ico.translation.32"/><bt:Image size="80" resid="ico.translation.80"/></Icon>
                  <Action xsi:type="ShowTaskpane">
                    <TaskpaneId>BIP</TaskpaneId>
                    <SourceLocation resid="url.translation"/>
                  </Action>
                </Control>

                <Control xsi:type="Button" id="btnExport">
                  <Label resid="lbl.export"/>
                  <Supertip><Title resid="lbl.export"/><Description resid="tip.export"/></Supertip>
                  <Icon><bt:Image size="16" resid="ico.export.16"/><bt:Image size="32" resid="ico.export.32"/><bt:Image size="80" resid="ico.export.80"/></Icon>
                  <Action xsi:type="ShowTaskpane">
                    <TaskpaneId>BIP</TaskpaneId>
                    <SourceLocation resid="url.export"/>
                  </Action>
                </Control>
              </Group>

              <!-- ============ OPTIONS (3 buttons) ============ -->
              <Group id="grpOptions">
                <Label resid="grp.options"/>
                <Icon><bt:Image size="16" resid="ico.options.16"/><bt:Image size="32" resid="ico.options.32"/><bt:Image size="80" resid="ico.options.80"/></Icon>

                <Control xsi:type="Button" id="btnOptions">
                  <Label resid="lbl.options"/>
                  <Supertip><Title resid="lbl.options"/><Description resid="tip.options"/></Supertip>
                  <Icon><bt:Image size="16" resid="ico.options.16"/><bt:Image size="32" resid="ico.options.32"/><bt:Image size="80" resid="ico.options.80"/></Icon>
                  <Action xsi:type="ShowTaskpane">
                    <TaskpaneId>BIP</TaskpaneId>
                    <SourceLocation resid="url.options"/>
                  </Action>
                </Control>

                <Control xsi:type="Button" id="btnHelp">
                  <Label resid="lbl.help"/>
                  <Supertip><Title resid="lbl.help"/><Description resid="tip.help"/></Supertip>
                  <Icon><bt:Image size="16" resid="ico.help.16"/><bt:Image size="32" resid="ico.help.32"/><bt:Image size="80" resid="ico.help.80"/></Icon>
                  <Action xsi:type="ShowTaskpane">
                    <TaskpaneId>BIP</TaskpaneId>
                    <SourceLocation resid="url.help"/>
                  </Action>
                </Control>

                <Control xsi:type="Button" id="btnAbout">
                  <Label resid="lbl.about"/>
                  <Supertip><Title resid="lbl.about"/><Description resid="tip.about"/></Supertip>
                  <Icon><bt:Image size="16" resid="ico.about.16"/><bt:Image size="32" resid="ico.about.32"/><bt:Image size="80" resid="ico.about.80"/></Icon>
                  <Action xsi:type="ShowTaskpane">
                    <TaskpaneId>BIP</TaskpaneId>
                    <SourceLocation resid="url.about"/>
                  </Action>
                </Control>
              </Group>

              <Label resid="tab.publisher"/>
            </CustomTab>
          </ExtensionPoint>

          <!-- Right-click context menu: individual buttons (Mac compatible) -->
          <ExtensionPoint xsi:type="ContextMenu">
            <OfficeMenu id="ContextMenuText">
              <Control xsi:type="Button" id="ctxFieldProps">
                <Label resid="lbl.ctx.props"/>
                <Supertip><Title resid="lbl.ctx.props"/><Description resid="tip.ctx.props"/></Supertip>
                <Icon><bt:Image size="16" resid="ico.fieldbrowser.16"/><bt:Image size="32" resid="ico.fieldbrowser.32"/><bt:Image size="80" resid="ico.fieldbrowser.80"/></Icon>
                <Action xsi:type="ExecuteFunction"><FunctionName>cmdFieldProperties</FunctionName></Action>
              </Control>
              <Control xsi:type="Button" id="ctxInsertField">
                <Label resid="lbl.ctx.field"/>
                <Supertip><Title resid="lbl.ctx.field"/><Description resid="tip.ctx.field"/></Supertip>
                <Icon><bt:Image size="16" resid="ico.field.16"/><bt:Image size="32" resid="ico.field.32"/><bt:Image size="80" resid="ico.field.80"/></Icon>
                <Action xsi:type="ExecuteFunction"><FunctionName>cmdInsertFieldAtSelection</FunctionName></Action>
              </Control>
              <Control xsi:type="Button" id="ctxRepGroup">
                <Label resid="lbl.ctx.repgroup"/>
                <Supertip><Title resid="lbl.ctx.repgroup"/><Description resid="tip.ctx.repgroup"/></Supertip>
                <Icon><bt:Image size="16" resid="ico.repgroup.16"/><bt:Image size="32" resid="ico.repgroup.32"/><bt:Image size="80" resid="ico.repgroup.80"/></Icon>
                <Action xsi:type="ExecuteFunction"><FunctionName>cmdWrapRepeatingGroup</FunctionName></Action>
              </Control>
              <Control xsi:type="Button" id="ctxCondRegion">
                <Label resid="lbl.ctx.condreg"/>
                <Supertip><Title resid="lbl.ctx.condreg"/><Description resid="tip.ctx.condreg"/></Supertip>
                <Icon><bt:Image size="16" resid="ico.condreg.16"/><bt:Image size="32" resid="ico.condreg.32"/><bt:Image size="80" resid="ico.condreg.80"/></Icon>
                <Action xsi:type="ExecuteFunction"><FunctionName>cmdWrapConditionalRegion</FunctionName></Action>
              </Control>
              <Control xsi:type="Button" id="ctxCondFmt">
                <Label resid="lbl.ctx.condfmt"/>
                <Supertip><Title resid="lbl.ctx.condfmt"/><Description resid="tip.ctx.condfmt"/></Supertip>
                <Icon><bt:Image size="16" resid="ico.condfmt.16"/><bt:Image size="32" resid="ico.condfmt.32"/><bt:Image size="80" resid="ico.condfmt.80"/></Icon>
                <Action xsi:type="ExecuteFunction"><FunctionName>cmdWrapConditionalFormat</FunctionName></Action>
              </Control>
            </OfficeMenu>
          </ExtensionPoint>

        </DesktopFormFactor>
      </Host>
    </Hosts>

    <Resources>
      <bt:Images>
        <bt:Image id="ico.samplexml.16"    DefaultValue="https://localhost:3000/images/ico-samplexml-16.png"/>
        <bt:Image id="ico.samplexml.32"    DefaultValue="https://localhost:3000/images/ico-samplexml-32.png"/>
        <bt:Image id="ico.samplexml.80"    DefaultValue="https://localhost:3000/images/ico-samplexml-80.png"/>
        <bt:Image id="ico.xmlschema.16"    DefaultValue="https://localhost:3000/images/ico-xmlschema-16.png"/>
        <bt:Image id="ico.xmlschema.32"    DefaultValue="https://localhost:3000/images/ico-xmlschema-32.png"/>
        <bt:Image id="ico.xmlschema.80"    DefaultValue="https://localhost:3000/images/ico-xmlschema-80.png"/>
        <bt:Image id="ico.field.16"        DefaultValue="https://localhost:3000/images/ico-field-16.png"/>
        <bt:Image id="ico.field.32"        DefaultValue="https://localhost:3000/images/ico-field-32.png"/>
        <bt:Image id="ico.field.80"        DefaultValue="https://localhost:3000/images/ico-field-80.png"/>
        <bt:Image id="ico.tablewiz.16"     DefaultValue="https://localhost:3000/images/ico-tablewiz-16.png"/>
        <bt:Image id="ico.tablewiz.32"     DefaultValue="https://localhost:3000/images/ico-tablewiz-32.png"/>
        <bt:Image id="ico.tablewiz.80"     DefaultValue="https://localhost:3000/images/ico-tablewiz-80.png"/>
        <bt:Image id="ico.chart.16"        DefaultValue="https://localhost:3000/images/ico-chart-16.png"/>
        <bt:Image id="ico.chart.32"        DefaultValue="https://localhost:3000/images/ico-chart-32.png"/>
        <bt:Image id="ico.chart.80"        DefaultValue="https://localhost:3000/images/ico-chart-80.png"/>
        <bt:Image id="ico.pivot.16"        DefaultValue="https://localhost:3000/images/ico-pivot-16.png"/>
        <bt:Image id="ico.pivot.32"        DefaultValue="https://localhost:3000/images/ico-pivot-32.png"/>
        <bt:Image id="ico.pivot.80"        DefaultValue="https://localhost:3000/images/ico-pivot-80.png"/>
        <bt:Image id="ico.allfields.16"    DefaultValue="https://localhost:3000/images/ico-allfields-16.png"/>
        <bt:Image id="ico.allfields.32"    DefaultValue="https://localhost:3000/images/ico-allfields-32.png"/>
        <bt:Image id="ico.allfields.80"    DefaultValue="https://localhost:3000/images/ico-allfields-80.png"/>
        <bt:Image id="ico.tableform.16"    DefaultValue="https://localhost:3000/images/ico-tableform-16.png"/>
        <bt:Image id="ico.tableform.32"    DefaultValue="https://localhost:3000/images/ico-tableform-32.png"/>
        <bt:Image id="ico.tableform.80"    DefaultValue="https://localhost:3000/images/ico-tableform-80.png"/>
        <bt:Image id="ico.repgroup.16"     DefaultValue="https://localhost:3000/images/ico-repgroup-16.png"/>
        <bt:Image id="ico.repgroup.32"     DefaultValue="https://localhost:3000/images/ico-repgroup-32.png"/>
        <bt:Image id="ico.repgroup.80"     DefaultValue="https://localhost:3000/images/ico-repgroup-80.png"/>
        <bt:Image id="ico.condfmt.16"      DefaultValue="https://localhost:3000/images/ico-condfmt-16.png"/>
        <bt:Image id="ico.condfmt.32"      DefaultValue="https://localhost:3000/images/ico-condfmt-32.png"/>
        <bt:Image id="ico.condfmt.80"      DefaultValue="https://localhost:3000/images/ico-condfmt-80.png"/>
        <bt:Image id="ico.condreg.16"      DefaultValue="https://localhost:3000/images/ico-condreg-16.png"/>
        <bt:Image id="ico.condreg.32"      DefaultValue="https://localhost:3000/images/ico-condreg-32.png"/>
        <bt:Image id="ico.condreg.80"      DefaultValue="https://localhost:3000/images/ico-condreg-80.png"/>
        <bt:Image id="ico.preview.16"      DefaultValue="https://localhost:3000/images/ico-preview-16.png"/>
        <bt:Image id="ico.preview.32"      DefaultValue="https://localhost:3000/images/ico-preview-32.png"/>
        <bt:Image id="ico.preview.80"      DefaultValue="https://localhost:3000/images/ico-preview-80.png"/>
        <bt:Image id="ico.fieldbrowser.16" DefaultValue="https://localhost:3000/images/ico-fieldbrowser-16.png"/>
        <bt:Image id="ico.fieldbrowser.32" DefaultValue="https://localhost:3000/images/ico-fieldbrowser-32.png"/>
        <bt:Image id="ico.fieldbrowser.80" DefaultValue="https://localhost:3000/images/ico-fieldbrowser-80.png"/>
        <bt:Image id="ico.validate.16"     DefaultValue="https://localhost:3000/images/ico-validate-16.png"/>
        <bt:Image id="ico.validate.32"     DefaultValue="https://localhost:3000/images/ico-validate-32.png"/>
        <bt:Image id="ico.validate.80"     DefaultValue="https://localhost:3000/images/ico-validate-80.png"/>
        <bt:Image id="ico.a11y.16"         DefaultValue="https://localhost:3000/images/ico-a11y-16.png"/>
        <bt:Image id="ico.a11y.32"         DefaultValue="https://localhost:3000/images/ico-a11y-32.png"/>
        <bt:Image id="ico.a11y.80"         DefaultValue="https://localhost:3000/images/ico-a11y-80.png"/>
        <bt:Image id="ico.translation.16"  DefaultValue="https://localhost:3000/images/ico-translation-16.png"/>
        <bt:Image id="ico.translation.32"  DefaultValue="https://localhost:3000/images/ico-translation-32.png"/>
        <bt:Image id="ico.translation.80"  DefaultValue="https://localhost:3000/images/ico-translation-80.png"/>
        <bt:Image id="ico.export.16"       DefaultValue="https://localhost:3000/images/ico-export-16.png"/>
        <bt:Image id="ico.export.32"       DefaultValue="https://localhost:3000/images/ico-export-32.png"/>
        <bt:Image id="ico.export.80"       DefaultValue="https://localhost:3000/images/ico-export-80.png"/>
        <bt:Image id="ico.options.16"      DefaultValue="https://localhost:3000/images/ico-options-16.png"/>
        <bt:Image id="ico.options.32"      DefaultValue="https://localhost:3000/images/ico-options-32.png"/>
        <bt:Image id="ico.options.80"      DefaultValue="https://localhost:3000/images/ico-options-80.png"/>
        <bt:Image id="ico.help.16"         DefaultValue="https://localhost:3000/images/ico-help-16.png"/>
        <bt:Image id="ico.help.32"         DefaultValue="https://localhost:3000/images/ico-help-32.png"/>
        <bt:Image id="ico.help.80"         DefaultValue="https://localhost:3000/images/ico-help-80.png"/>
        <bt:Image id="ico.about.16"        DefaultValue="https://localhost:3000/images/ico-about-16.png"/>
        <bt:Image id="ico.about.32"        DefaultValue="https://localhost:3000/images/ico-about-32.png"/>
        <bt:Image id="ico.about.80"        DefaultValue="https://localhost:3000/images/ico-about-80.png"/>
      </bt:Images>
      <bt:Urls>
        <bt:Url id="url.commands"     DefaultValue="https://localhost:3000/commands.html"/>
        <bt:Url id="url.taskpane"     DefaultValue="https://localhost:3000/taskpane.html"/>
        <bt:Url id="url.samplexml"    DefaultValue="https://localhost:3000/taskpane.html?panel=sample-xml"/>
        <bt:Url id="url.xmlschema"    DefaultValue="https://localhost:3000/taskpane.html?panel=xml-schema"/>
        <bt:Url id="url.field"        DefaultValue="https://localhost:3000/taskpane.html?panel=insert-field"/>
        <bt:Url id="url.tablewiz"     DefaultValue="https://localhost:3000/taskpane.html?panel=table-wizard"/>
        <bt:Url id="url.chart"        DefaultValue="https://localhost:3000/taskpane.html?panel=chart"/>
        <bt:Url id="url.pivot"        DefaultValue="https://localhost:3000/taskpane.html?panel=pivot-table"/>
        <bt:Url id="url.preview"      DefaultValue="https://localhost:3000/taskpane.html?panel=preview"/>
        <bt:Url id="url.fieldbrowser" DefaultValue="https://localhost:3000/taskpane.html?panel=field-browser"/>
        <bt:Url id="url.validate"     DefaultValue="https://localhost:3000/taskpane.html?panel=validate-template"/>
        <bt:Url id="url.a11y"         DefaultValue="https://localhost:3000/taskpane.html?panel=accessibility"/>
        <bt:Url id="url.translation"  DefaultValue="https://localhost:3000/taskpane.html?panel=translation"/>
        <bt:Url id="url.export"       DefaultValue="https://localhost:3000/taskpane.html?panel=export"/>
        <bt:Url id="url.options"      DefaultValue="https://localhost:3000/taskpane.html?panel=options"/>
        <bt:Url id="url.help"         DefaultValue="https://localhost:3000/taskpane.html?panel=help"/>
        <bt:Url id="url.about"        DefaultValue="https://localhost:3000/taskpane.html?panel=about"/>
      </bt:Urls>
      <bt:ShortStrings>
        <bt:String id="tab.publisher"    DefaultValue="Publisher"/>
        <bt:String id="grp.data"         DefaultValue="Load Data"/>
        <bt:String id="grp.insert"       DefaultValue="Insert"/>
        <bt:String id="grp.preview"      DefaultValue="Preview"/>
        <bt:String id="grp.tools"        DefaultValue="Tools"/>
        <bt:String id="grp.options"      DefaultValue="Options"/>
        <bt:String id="lbl.samplexml"    DefaultValue="Sample XML"/>
        <bt:String id="lbl.xmlschema"    DefaultValue="XML Schema"/>
        <bt:String id="lbl.field"        DefaultValue="Field"/>
        <bt:String id="lbl.tablewiz"     DefaultValue="Table Wizard"/>
        <bt:String id="lbl.chart"        DefaultValue="Chart"/>
        <bt:String id="lbl.pivot"        DefaultValue="Pivot Table"/>
        <bt:String id="lbl.more"         DefaultValue="More..."/>
        <bt:String id="lbl.tableform"    DefaultValue="Table/Form"/>
        <bt:String id="lbl.repgroup"     DefaultValue="Repeating Group"/>
        <bt:String id="lbl.condfmt"      DefaultValue="Conditional Format"/>
        <bt:String id="lbl.condreg"      DefaultValue="Conditional Region"/>
        <bt:String id="lbl.allfields"    DefaultValue="All Fields"/>
        <bt:String id="lbl.preview"      DefaultValue="Preview"/>
        <bt:String id="lbl.fieldbrowser" DefaultValue="Field Browser"/>
        <bt:String id="lbl.validate"     DefaultValue="Validate"/>
        <bt:String id="lbl.a11y"         DefaultValue="Accessibility"/>
        <bt:String id="lbl.translation"  DefaultValue="Translation"/>
        <bt:String id="lbl.export"       DefaultValue="Export"/>
        <bt:String id="lbl.options"      DefaultValue="Options"/>
        <bt:String id="lbl.help"         DefaultValue="Help"/>
        <bt:String id="lbl.about"        DefaultValue="About"/>
        <bt:String id="getStarted.Title" DefaultValue="BI Publisher Template Builder"/>
        <bt:String id="lbl.ctx.props"    DefaultValue="BIP: Field Properties..."/>
        <bt:String id="lbl.ctx.field"    DefaultValue="BIP: Insert Field"/>
        <bt:String id="lbl.ctx.repgroup" DefaultValue="BIP: Repeating Group"/>
        <bt:String id="lbl.ctx.condreg"  DefaultValue="BIP: Conditional Region"/>
        <bt:String id="lbl.ctx.condfmt"  DefaultValue="BIP: Conditional Format"/>
      </bt:ShortStrings>
      <bt:LongStrings>
        <bt:String id="tip.samplexml"    DefaultValue="Load sample XML data file"/>
        <bt:String id="tip.xmlschema"    DefaultValue="Load an XML Schema (.xsd) file"/>
        <bt:String id="tip.field"        DefaultValue="Insert a data field placeholder"/>
        <bt:String id="tip.tablewiz"     DefaultValue="Step-by-step wizard to create data tables"/>
        <bt:String id="tip.chart"        DefaultValue="Insert a chart to visualize data"/>
        <bt:String id="tip.pivot"        DefaultValue="Create a cross-tabulation (pivot table)"/>
        <bt:String id="tip.more"         DefaultValue="Table/Form, Repeating Group, Conditional Format/Region, All Fields"/>
        <bt:String id="tip.tableform"    DefaultValue="Insert a table or form layout"/>
        <bt:String id="tip.repgroup"     DefaultValue="Define repeating sections"/>
        <bt:String id="tip.condfmt"      DefaultValue="Apply formatting based on conditions"/>
        <bt:String id="tip.condreg"      DefaultValue="Show or hide regions based on conditions"/>
        <bt:String id="tip.allfields"    DefaultValue="Insert all fields from the data source"/>
        <bt:String id="tip.preview"      DefaultValue="Preview template in various output formats"/>
        <bt:String id="tip.fieldbrowser" DefaultValue="Browse and edit template fields"/>
        <bt:String id="tip.validate"     DefaultValue="Validate template for errors"/>
        <bt:String id="tip.a11y"         DefaultValue="Check template accessibility"/>
        <bt:String id="tip.translation"  DefaultValue="Translation and localization tools"/>
        <bt:String id="tip.export"       DefaultValue="Export template in various formats"/>
        <bt:String id="tip.options"      DefaultValue="Configure add-in preferences"/>
        <bt:String id="tip.help"         DefaultValue="Open help documentation"/>
        <bt:String id="tip.about"        DefaultValue="About BI Publisher Template Builder"/>
        <bt:String id="getStarted.Desc"  DefaultValue="Design Oracle BI Publisher report templates directly in Word."/>
        <bt:String id="tip.ctx.props"    DefaultValue="View and edit properties of the selected BI Publisher field"/>
        <bt:String id="tip.ctx.field"    DefaultValue="Insert a BI Publisher field tag at cursor position"/>
        <bt:String id="tip.ctx.repgroup" DefaultValue="Wrap selected text in a repeating group"/>
        <bt:String id="tip.ctx.condreg"  DefaultValue="Wrap selected text in a conditional region"/>
        <bt:String id="tip.ctx.condfmt"  DefaultValue="Apply conditional formatting to selected text"/>
      </bt:LongStrings>
    </Resources>
  </VersionOverrides>
</OfficeApp>
